fplcli/__init__.py
fplcli/classic_league_standings.py
fplcli/cli.py
fplcli/cliprinter.py
fplcli/configure.py
fplcli/constants.py
fplcli/element_stats.py
fplcli/element_type.py
fplcli/entry.py
fplcli/fixture.py
fplcli/fplapi.py
fplcli/gameweek.py
fplcli/league.py
fplcli/picks.py
fplcli/player.py
fplcli/urls.py
fplcli-0.1.9.dist-info/METADATA
fplcli-0.1.9.dist-info/RECORD
fplcli-0.1.9.dist-info/WHEEL
fplcli-0.1.9.dist-info/entry_points.txt
fplcli-0.1.9.dist-info/top_level.txt
