Metadata-Version: 2.1
Name: fplcli
Version: 0.1.9
Summary: A CLI tool for Fantasy Premier League
Home-page: https://github.com/janerikcarlsen/fpl-cli
Author: Jan-Erik Carlsen
Author-email: jan.erik.carlsen@gmail.com
License: UNKNOWN
Project-URL: Docs, https://pypi.org/project/fplcli/
Project-URL: Source, https://github.com/janerikcarlsen/fpl-cli
Platform: UNKNOWN
Classifier: Programming Language :: Python :: 2
Classifier: Programming Language :: Python :: 2.7
Classifier: Programming Language :: Python :: 3
Classifier: Programming Language :: Python :: 3.4
Classifier: Programming Language :: Python :: 3.5
Classifier: Programming Language :: Python :: 3.6
Classifier: Programming Language :: Python :: 3.7
Classifier: License :: OSI Approved :: MIT License
Classifier: Operating System :: OS Independent
Classifier: Development Status :: 3 - Alpha
Classifier: Intended Audience :: Science/Research
Classifier: Intended Audience :: End Users/Desktop
Classifier: Intended Audience :: Developers
Classifier: Topic :: Games/Entertainment
Requires-Dist: requests
Requires-Dist: future
Requires-Dist: click
Requires-Dist: pyfiglet
Requires-Dist: six
Requires-Dist: Prettytable
Requires-Dist: termcolor
Requires-Dist: colorama
Requires-Dist: configparser
